fullcpu/mux.sv
module mux #(
    parameter DATA_WIDTH = 32
)(
    // interface signals
    input logic   [DATA_WIDTH-1:0]        d0,     // regOp2
    input logic   [DATA_WIDTH-1:0]        d1,     // ImmOp
    input logic                           s,      // ALUsrc
    output logic  [DATA_WIDTH-1:0]        out    // ALUop2
);

    // output logic
    assign out = s ? d1 : d0;

endmodule

fullcpu/datamem.sv
module datamem#(
    parameter   ADDRESS_WIDTH = 32,
                DATA_WIDTH = 32
)(
    input logic clk,
    input logic WE,
    input logic [ADDRESS_WIDTH-1:0] A,
    input logic [DATA_WIDTH-1:0] WD,
    output logic [DATA_WIDTH-1:0] RD 
);

logic [DATA_WIDTH-1:0] ram_array [255:0];

assign ram_array[255] = 32'h12345; // a0 should be 12345 after FE

always_ff @(posedge clk) begin 
    if(WE == 1'b1)
        ram_array[A] <= WD;
end
assign RD = ram_array [A];
endmodule

fullcpu/alu.sv
module alu #(
    parameter DATA_WIDTH = 32
)(
    // interface signals
    input logic        [DATA_WIDTH-1:0]         ALUSrcA,       
    input logic        [DATA_WIDTH-1:0]         ALUSrcB,       
    input logic        [2:0]                    ALUControl,      
    output logic                                Zero,
    output logic       [DATA_WIDTH-1:0]         ALUResult           
);

    always_comb begin
        case (ALUControl)
            // Sum
            3'b000: ALUResult  = ALUSrcA + ALUSrcB;
            // Subtract
            3'b001: ALUResult  = ALUSrcA - ALUSrcB;
            // And
            3'b010: ALUResult  = ALUSrcA & ALUSrcB;
            // Or
            3'b011: ALUResult  = ALUSrcA | ALUSrcB;
            // SLT
            // 3'b100: ALUResult  = ALUSrcA < ALUSrcB;
            // gives error messages
            // Xor
            3'b101: ALUResult  = ALUSrcA ^ ALUSrcB;
            // SLL
            3'b110: ALUResult  = ALUSrcA << ALUSrcB;
            // SRL
            3'b111: ALUResult  = ALUSrcA >> ALUSrcB;

        endcase
        
        // Zero
        if(ALUSrcA == ALUSrcB)
            Zero = 1;
        else 
            Zero = 0;
        
    end

endmodule

fullcpu/regfile.sv
module regfile #(
    parameter ADDRESS_WIDTH = 5,
    parameter DATA_WIDTH = 32
)(
    // interface signals
    input logic                           clk,
    input logic   [ADDRESS_WIDTH-1:0]     A1,     // rs1
    input logic   [ADDRESS_WIDTH-1:0]     A2,     // rs2
    input logic   [ADDRESS_WIDTH-1:0]     A3,     // rd
    input logic                           WE3,    // RegWrite
    input logic   [DATA_WIDTH-1:0]        WD3,    // ALUout
    output logic  [DATA_WIDTH-1:0]        RD1,
    output logic  [DATA_WIDTH-1:0]        RD2,
    output logic  [DATA_WIDTH-1:0]        a0      // Used for testing purposes
);

    // state registers
    logic [DATA_WIDTH-1:0] ram_array [2**ADDRESS_WIDTH-1:0];

    always_ff @(posedge clk) begin
        if (WE3) ram_array[A3] <= WD3; 
    end

    always_comb begin
        RD1 = (A1 == 0) ? 0 : ram_array[A1];
        RD2 = (A2 == 0) ? 0 : ram_array[A2];
        a0 = ram_array[10];                      // Used for testing purposes
    end

endmodule

fullcpu/topregalu.sv
module topregalu #(
    parameter   DATA_WIDTH = 32,
                ADDRESS_WIDTH = 5
)(
    // interface signals
    input logic                                      clk,
    input logic        [ADDRESS_WIDTH-1:0]           rs1,           
    input logic        [ADDRESS_WIDTH-1:0]           rs2,      
    input logic        [ADDRESS_WIDTH-1:0]           rd,
    input logic                                      RegWrite,
    input logic                                      ALUsrc,
    input logic                                      ResultSrc,
    input logic                                      MemWrite,   
    input logic        [2:0]                         ALUCtrl,
    input logic        [DATA_WIDTH-1:0]              ImmOp,
    input logic        [32:0]                        PC,
    input logic                                      jalmuxSel, // select for the jalmux
    output logic                                     eq,
    output logic       [DATA_WIDTH-1:0]              a0
);

logic [DATA_WIDTH-1:0] ALUout;
logic [DATA_WIDTH-1:0] ALUop1;
logic [DATA_WIDTH-1:0] ALUop2;
logic [DATA_WIDTH-1:0] regOp2;
logic [DATA_WIDTH-1:0] ReadData;
logic [DATA_WIDTH-1:0] Results; // output from the result mux
logic [DATA_WIDTH-1:0] jalmuxOut; // output from jalmux

regfile RegFile (
    .clk(clk),
    .A1(rs1),
    .A2(rs2),
    .A3(rd),
    .WE3(RegWrite),
    .WD3(jalmuxOut),
    .RD1(ALUop1),
    .RD2(regOp2),
    .a0(a0)
);

alu ALU(
    .ALUSrcA(ALUop1),
    .ALUSrcB(ALUop2),
    .ALUControl(ALUCtrl),
    .Zero(eq),
    .ALUResult(ALUout)
);

mux MUX(
    .d0(regOp2),
    .d1(ImmOp),
    .s(ALUsrc),
    .out(ALUop2)
);

datamem datamemory(
    .clk(clk),
    .WE(MemWrite),
    .A(ALUout),
    .WD(regOp2),
    .RD(ReadData)
);

mux ResultMux(
    .d0(ALUout),
    .d1(ReadData),
    .s(ResultSrc),
    .out(Results)
);

mux jalmux(
    .d0(Results),
    .d1(PC+4),
    .s(jalmuxSel),
    .out(jalmuxOut)
);

endmodule

fullcpu/sign_extend.sv
module sign_extend #(
    parameter ADDRESS_WIDTH = 32
)(
    input logic     [ADDRESS_WIDTH-1:0]   instr,
    input logic                   [2:0]  ImmSrc,
    output logic    [ADDRESS_WIDTH-1:0]   ImmExt
);

always_comb begin
    case(ImmSrc)
        // I-type
        3'b000: ImmExt[31:0] = {{20{instr[ADDRESS_WIDTH-1]}}, instr[ADDRESS_WIDTH-1:20]};
        // S-type
        3'b001: ImmExt[31:0] = {{20{instr[ADDRESS_WIDTH-1]}}, instr[ADDRESS_WIDTH-1:25], instr[11:7]};
        // B-type
        3'b010: ImmExt[31:0] = {{20{instr[ADDRESS_WIDTH-1]}}, instr[7], instr[30:25], instr[11:8], 1'b0};
        // R-type
        3'b011: ImmExt[31:0] = instr;
        // J-type
        3'b100: ImmExt[31:0] = {{11{instr[31]}}, instr[31], instr[19:12], instr[20], instr[30:21], 1'b0};
        // U-type
        3'b101: ImmExt[31:0] = {instr[31:12], {12{instr[12]}}};
        // JALR 
        3'b110: ImmExt[31:0] = {{20{instr[31]}},instr[31:20]};

    endcase
    
end

endmodule

fullcpu/control_unit.sv
module control_unit #(
    parameter ADDRESS_WIDTH = 32
)(
    input logic      [6:0]          op,  //output from Instr Mem
    input logic      [3:0]      funct3,
    input logic                 funct7,
    input logic                   Zero,
    output logic              RegWrite,
    output logic     [2:0]     ALUctrl,
    output logic                ALUsrc,
    output logic     [2:0]      ImmSrc,
    output logic                 PCsrc,
    output logic              MemWrite,
    output logic             ResultSrc,
    output logic             jalmuxSel
);

always_comb begin

    // Initialising Outputs
    RegWrite = 1'b0;
    ImmSrc = 3'b000;
    ALUctrl = 3'b000;
    ALUsrc = 1'b0;
    PCsrc = 1'b0; 
    MemWrite = 1'b0;
    ResultSrc = 1'b0;
    jalmuxSel = 1'b0;

    /* if(op == 7'b0110011) // 3 Register Instructions
        if(funct7 == 0)
            if(funct3 == 3'b000) // add
            if(funct3 == 3'b001) // shift left logical
            if(funct3 == 3'b010) // set less than
            if(funct3 == 3'b011) // set less than unsigned
            if(funct3 == 3'b100) // xor
            if(funct3 == 3'b101) // shift right logical
            if(funct3 == 3'b110) // or
            if(funct3 == 3'b111) // and
        if(funct7 == 1)
            if(funct3 == 3'b000) // sub
            if(funct3 == 3'b101) // shift right arithmetic

    if(op == 7'b0000011) // Load Instructions
        if(funct3 == 3'b000) // load byte
        if(funct3 == 3'b001) // load half
        if(funct3 == 3'b010) // load word
        if(funct3 == 3'b100) // load byte unsigned
        if(funct3 == 3'b101) // load half unsigned
    
    if(op == 7'b0010011) // Immediate Instructions
        if(funct3 == 3'b000) // add immediate
        if(funct7 == 0)
            if(funct3 == 3'b001) // shift left logical immediate
            if(funct3 == 3'b101) // shift right logical immediate
        if(funct7 == 1) 
            if(funct3 == 3'b101) // shift right arithmetic immediate
        if(funct3 == 3'b010) // set less than immediate
        if(funct3 == 3'b011) // set less than immediate unsigned
        if(funct3 == 3'b100) // xor immediate
        if(funct3 == 3'b110) // or immediate
        if(funct3 == 3'b111) // and immediate
    
    if(op == 7'b0100011) // Store Instructions
        if(funct3 == 3'b000) // store byte
        if(funct3 == 3'b001) // store half
        if(funct3 == 3'b010) // store word

    if(op == 7'b1100011) // Branch Instructions
        if(funct3 == 3'b000) // branch if equal
        if(funct3 == 3'b001) // branch if not equal
        if(funct3 == 3'b100) // branch if less than
        if(funct3 == 3'b101) // branch if greater than or equal
        if(funct3 == 3'b110) // branch if less than unsigned
        if(funct3 == 3'b111) // branch if greater than or equal unsigned

    if(op == 7'b001011) // add upper immediate to PC

    if(op == 7'b0110111) // load upper immediate

    if(op == 7'b1100111) 
        if(funct3 == 3'b000) // jump and link register*/
    
    case (op)
        7'b0010011: // register instructions
            case(funct3)
                3'b000: // addi
                    begin 
                        RegWrite = 1'b1;
                        ImmSrc = 3'b000;
                        ALUctrl = 3'b000;
                        ALUsrc = 1'b1;
                    end

                3'b001: // SLLI
                    begin
                        RegWrite = 1'b1;
                        ImmSrc = 3'b000;
                        ALUctrl = 3'b110;
                        ALUsrc = 1'b1;   
                    end
            endcase

        7'b1100011: // branch instructions
            case(funct3)
                3'b001: // bne
                if(Zero == 1'b0)
                    begin
                        ImmSrc = 3'b010;
                        PCsrc = 1'b1;
                    end

                3'b000: // beq
                    if (Zero == 1'b1)
                        begin
                        PCsrc = 1'b1;
                        ImmSrc = 3'b010;
                        end
                    else
                        PCsrc = 1'b0;

            endcase

        7'b0100011: // store instructions
            case(funct3)
                3'b010: // sw
                    MemWrite = 1'b1;
            endcase

        7'b0000011: // load instructions
            case(funct3)
                3'b010: // lw
                    begin
                        ResultSrc = 1'b1;
                        RegWrite = 1'b1;
                    end
            endcase
        
        7'b1101111: // jal
            begin
                ImmSrc = 3'b100;
                jalmuxSel = 1'b1;
                RegWrite = 1'b1;
            end
    endcase
end 

endmodule

fullcpu/instr_mem.sv
module instr_mem #(
    parameter   ADDRESS_WIDTH = 32, // testing
                DATAOUT_WIDTH = 32,
                DATA_WIDTH = 8
)(
    input logic  [ADDRESS_WIDTH-1:0] A,
    output logic [DATAOUT_WIDTH-1:0] RD
);

logic [DATA_WIDTH-1:0] rom_array [32'hBFC00FFF:32'hBFC00000]; // 32 bits

initial begin
        
        $display("Loading rom.");
        $readmemh("test.mem", rom_array,32'hBFC00000);
end;

assign RD = {rom_array [A], rom_array [A+1], rom_array [A+2], rom_array [A+3]};

endmodule

fullcpu/blue_part.sv
module blue_part #(
    parameter address_width = 32
)(
    input logic                            PCsrc, // output from control unit
    input logic                            clk,
    input logic                            rst,
    input logic [address_width-1:0]        ImmOp, // output from "sign extend" block
    output logic [address_width-1:0]       PC
);

//logic       next_pc;

always_ff@(posedge clk) begin
    if (rst)        PC <= {address_width{1'b0}};
    else if (PCsrc)      PC <= PC + ImmOp;
    else            PC <= PC + 4;
end

endmodule

fullcpu/top.sv
module top#(
    parameter ADDRESS_WIDTH = 32,
    DATAOUT_WIDTH = 32
)(
    input logic                            PCsrc, // output from control unit
    input logic                            clk,
    input logic                            rst,
    input logic [DATAOUT_WIDTH-1:0]        ImmOp, // output from "sign extend" block
  //  output logic [ADDRESS_WIDTH-1:0]       PC,
  //  input logic [ADDRESS_WIDTH-1:0]        A,
    output logic [DATAOUT_WIDTH-1:0]       RD,
    output logic [ADDRESS_WIDTH-1:0]       PC_out
);

logic [ADDRESS_WIDTH-1:0]        A;

blue_part pc(
    .PCsrc(PCsrc),
    .clk(clk),
    .rst(rst),
    .ImmOp(ImmOp),
    .PC(A)
);

instr_mem mem(
    .A(A),
    .RD(RD)
);

assign PC_out = A;
endmodule

fullcpu/fullcpu.sv
module fullcpu#(
    parameter  DATA_WIDTH = 32
) (
    input logic clk,
    input logic rst,
    output [DATA_WIDTH-1:0] a0
);

logic PCsrc;
logic [DATA_WIDTH-1:0] ImmOp;
logic [DATA_WIDTH-1:0] Instr;
logic Zero;
logic RegWrite;
logic [2:0] ALUctrl;
logic ALUsrc;
logic [2:0] ImmSrc;
logic MemWrite;
logic ResultSrc;
logic PC;
logic jalmuxSel;

top blue(
    .PCsrc(PCsrc),
    .clk(clk),
    .rst(rst),
    .ImmOp(ImmOp),
    .RD(Instr), // output
    .PC_out(PC) // output 
);

control_unit controlunit(
    .op(Instr[6:0]),
    .funct3(Instr[14:12]),
    .funct7(Instr[30]),
    .Zero(Zero),
    .RegWrite(RegWrite),
    .ALUctrl(ALUctrl),
    .ALUsrc(ALUsrc),
    .ImmSrc(ImmSrc),
    .PCsrc(PCsrc),
    .MemWrite(MemWrite),
    .ResultSrc(ResultSrc),
    .jalmuxSel(jalmuxSel)
);

sign_extend signextend (
    .instr(Instr),
    .ImmSrc(ImmSrc),
    .ImmExt(ImmOp)
);

topregalu topregalu (
    .clk(clk),
    .rs1(Instr[19:15]),
    .rs2(Instr[24:20]),
    .rd(Instr[11:7]),
    .RegWrite(RegWrite),
    .PC(PC),
    .ALUsrc(ALUsrc),
    .ResultSrc(ResultSrc),
    .MemWrite(MemWrite),
    .ALUCtrl(ALUctrl),
    .ImmOp(ImmOp),
    .eq(Zero),
    .a0(a0),
    .jalmuxSel(jalmuxSel)
);

endmodule

fullcpu/fullcpu.vcd
$version Generated by VerilatedVcd $end
$date Fri Dec  2 11:52:49 2022 $end
$timescale 1ps $end

 $scope module TOP $end
  $var wire 32 _ a0 [31:0] $end
  $var wire  1 ] clk $end
  $var wire  1 ^ rst $end
  $scope module fullcpu $end
   $var wire  3 % ALUctrl [2:0] $end
   $var wire  1 & ALUsrc $end
   $var wire 32 c DATA_WIDTH [31:0] $end
   $var wire 32 X ImmOp [31:0] $end
   $var wire  3 Z ImmSrc [2:0] $end
   $var wire 32 # Instr [31:0] $end
   $var wire  1 ' MemWrite $end
   $var wire  1 ) PC $end
   $var wire  1 W PCsrc $end
   $var wire  1 $ RegWrite $end
   $var wire  1 ( ResultSrc $end
   $var wire  1 Y Zero $end
   $var wire 32 _ a0 [31:0] $end
   $var wire  1 ] clk $end
   $var wire  1 * jalmuxSel $end
   $var wire  1 ^ rst $end
   $scope module blue $end
    $var wire 32 + A [31:0] $end
    $var wire 32 c ADDRESS_WIDTH [31:0] $end
    $var wire 32 c DATAOUT_WIDTH [31:0] $end
    $var wire 32 X ImmOp [31:0] $end
    $var wire 32 + PC_out [31:0] $end
    $var wire  1 W PCsrc $end
    $var wire 32 # RD [31:0] $end
    $var wire  1 ] clk $end
    $var wire  1 ^ rst $end
    $scope module mem $end
     $var wire 32 + A [31:0] $end
     $var wire 32 c ADDRESS_WIDTH [31:0] $end
     $var wire 32 c DATAOUT_WIDTH [31:0] $end
     $var wire 32 d DATA_WIDTH [31:0] $end
     $var wire 32 # RD [31:0] $end
    $upscope $end
    $scope module pc $end
     $var wire 32 X ImmOp [31:0] $end
     $var wire 32 + PC [31:0] $end
     $var wire  1 W PCsrc $end
     $var wire 32 c address_width [31:0] $end
     $var wire  1 ] clk $end
     $var wire  1 ^ rst $end
    $upscope $end
   $upscope $end
   $scope module controlunit $end
    $var wire 32 c ADDRESS_WIDTH [31:0] $end
    $var wire  3 % ALUctrl [2:0] $end
    $var wire  1 & ALUsrc $end
    $var wire  3 Z ImmSrc [2:0] $end
    $var wire  1 ' MemWrite $end
    $var wire  1 W PCsrc $end
    $var wire  1 $ RegWrite $end
    $var wire  1 ( ResultSrc $end
    $var wire  1 Y Zero $end
    $var wire  4 - funct3 [3:0] $end
    $var wire  1 . funct7 $end
    $var wire  1 * jalmuxSel $end
    $var wire  7 , op [6:0] $end
   $upscope $end
   $scope module signextend $end
    $var wire 32 c ADDRESS_WIDTH [31:0] $end
    $var wire 32 X ImmExt [31:0] $end
    $var wire  3 Z ImmSrc [2:0] $end
    $var wire 32 # instr [31:0] $end
   $upscope $end
   $scope module topregalu $end
    $var wire 32 e ADDRESS_WIDTH [31:0] $end
    $var wire  3 % ALUCtrl [2:0] $end
    $var wire 32 4 ALUop1 [31:0] $end
    $var wire 32 \ ALUop2 [31:0] $end
    $var wire 32 [ ALUout [31:0] $end
    $var wire  1 & ALUsrc $end
    $var wire 32 c DATA_WIDTH [31:0] $end
    $var wire 32 X ImmOp [31:0] $end
    $var wire  1 ' MemWrite $end
    $var wire 33 2 PC [32:0] $end
    $var wire 32 ` ReadData [31:0] $end
    $var wire  1 $ RegWrite $end
    $var wire  1 ( ResultSrc $end
    $var wire 32 a Results [31:0] $end
    $var wire 32 _ a0 [31:0] $end
    $var wire  1 ] clk $end
    $var wire  1 Y eq $end
    $var wire 32 b jalmuxOut [31:0] $end
    $var wire  1 * jalmuxSel $end
    $var wire  5 1 rd [4:0] $end
    $var wire 32 5 regOp2 [31:0] $end
    $var wire  5 / rs1 [4:0] $end
    $var wire  5 0 rs2 [4:0] $end
    $scope module ALU $end
     $var wire  3 % ALUControl [2:0] $end
     $var wire 32 [ ALUResult [31:0] $end
     $var wire 32 4 ALUSrcA [31:0] $end
     $var wire 32 \ ALUSrcB [31:0] $end
     $var wire 32 c DATA_WIDTH [31:0] $end
     $var wire  1 Y Zero $end
    $upscope $end
    $scope module MUX $end
     $var wire 32 c DATA_WIDTH [31:0] $end
     $var wire 32 5 d0 [31:0] $end
     $var wire 32 X d1 [31:0] $end
     $var wire 32 \ out [31:0] $end
     $var wire  1 & s $end
    $upscope $end
    $scope module RegFile $end
     $var wire  5 / A1 [4:0] $end
     $var wire  5 0 A2 [4:0] $end
     $var wire  5 1 A3 [4:0] $end
     $var wire 32 e ADDRESS_WIDTH [31:0] $end
     $var wire 32 c DATA_WIDTH [31:0] $end
     $var wire 32 4 RD1 [31:0] $end
     $var wire 32 5 RD2 [31:0] $end
     $var wire 32 b WD3 [31:0] $end
     $var wire  1 $ WE3 $end
     $var wire 32 _ a0 [31:0] $end
     $var wire  1 ] clk $end
     $var wire 32 6 ram_array[0] [31:0] $end
     $var wire 32 @ ram_array[10] [31:0] $end
     $var wire 32 A ram_array[11] [31:0] $end
     $var wire 32 B ram_array[12] [31:0] $end
     $var wire 32 C ram_array[13] [31:0] $end
     $var wire 32 D ram_array[14] [31:0] $end
     $var wire 32 E ram_array[15] [31:0] $end
     $var wire 32 F ram_array[16] [31:0] $end
     $var wire 32 G ram_array[17] [31:0] $end
     $var wire 32 H ram_array[18] [31:0] $end
     $var wire 32 I ram_array[19] [31:0] $end
     $var wire 32 7 ram_array[1] [31:0] $end
     $var wire 32 J ram_array[20] [31:0] $end
     $var wire 32 K ram_array[21] [31:0] $end
     $var wire 32 L ram_array[22] [31:0] $end
     $var wire 32 M ram_array[23] [31:0] $end
     $var wire 32 N ram_array[24] [31:0] $end
     $var wire 32 O ram_array[25] [31:0] $end
     $var wire 32 P ram_array[26] [31:0] $end
     $var wire 32 Q ram_array[27] [31:0] $end
     $var wire 32 R ram_array[28] [31:0] $end
     $var wire 32 S ram_array[29] [31:0] $end
     $var wire 32 8 ram_array[2] [31:0] $end
     $var wire 32 T ram_array[30] [31:0] $end
     $var wire 32 U ram_array[31] [31:0] $end
     $var wire 32 9 ram_array[3] [31:0] $end
     $var wire 32 : ram_array[4] [31:0] $end
     $var wire 32 ; ram_array[5] [31:0] $end
     $var wire 32 < ram_array[6] [31:0] $end
     $var wire 32 = ram_array[7] [31:0] $end
     $var wire 32 > ram_array[8] [31:0] $end
     $var wire 32 ? ram_array[9] [31:0] $end
    $upscope $end
    $scope module ResultMux $end
     $var wire 32 c DATA_WIDTH [31:0] $end
     $var wire 32 [ d0 [31:0] $end
     $var wire 32 ` d1 [31:0] $end
     $var wire 32 a out [31:0] $end
     $var wire  1 ( s $end
    $upscope $end
    $scope module datamemory $end
     $var wire 32 [ A [31:0] $end
     $var wire 32 c ADDRESS_WIDTH [31:0] $end
     $var wire 32 c DATA_WIDTH [31:0] $end
     $var wire 32 ` RD [31:0] $end
     $var wire 32 5 WD [31:0] $end
     $var wire  1 ' WE $end
     $var wire  1 ] clk $end
    $upscope $end
    $scope module jalmux $end
     $var wire 32 c DATA_WIDTH [31:0] $end
     $var wire 32 a d0 [31:0] $end
     $var wire 32 V d1 [31:0] $end
     $var wire 32 b out [31:0] $end
     $var wire  1 * s $end
    $upscope $end
   $upscope $end
  $upscope $end
 $upscope $end
$enddefinitions $end


#0
b00000000000000000000000000000000 #
0$
b000 %
0&
0'
0(
0)
0*
b00000000000000000000000000000000 +
b0000000 ,
b0000 -
0.
b00000 /
b00000 0
b00000 1
b000000000000000000000000000000000 2
b00000000000000000000000000000000 4
b00000000000000000000000000000000 5
b00000000000000000000000000000000 6
b00000000000000000000000000000000 7
b00000000000000000000000000000000 8
b00000000000000000000000000000000 9
b00000000000000000000000000000000 :
b00000000000000000000000000000000 ;
b00000000000000000000000000000000 <
b00000000000000000000000000000000 =
b00000000000000000000000000000000 >
b00000000000000000000000000000000 ?
b00000000000000000000000000000000 @
b00000000000000000000000000000000 A
b00000000000000000000000000000000 B
b00000000000000000000000000000000 C
b00000000000000000000000000000000 D
b00000000000000000000000000000000 E
b00000000000000000000000000000000 F
b00000000000000000000000000000000 G
b00000000000000000000000000000000 H
b00000000000000000000000000000000 I
b00000000000000000000000000000000 J
b00000000000000000000000000000000 K
b00000000000000000000000000000000 L
b00000000000000000000000000000000 M
b00000000000000000000000000000000 N
b00000000000000000000000000000000 O
b00000000000000000000000000000000 P
b00000000000000000000000000000000 Q
b00000000000000000000000000000000 R
b00000000000000000000000000000000 S
b00000000000000000000000000000000 T
b00000000000000000000000000000000 U
b00000000000000000000000000000100 V
0W
b00000000000000000000000000000000 X
0Y
b000 Z
b00000000000000000000000000000000 [
b00000000000000000000000000000000 \
1]
0^
b00000000000000000000000000000000 _
b00000000000000000000000000000000 `
b00000000000000000000000000000000 a
b00000000000000000000000000000000 b
b00000000000000000000000000100000 c
b00000000000000000000000000001000 d
b00000000000000000000000000000101 e
#1
b00000000000000000000010000010011 #
1$
1&
b0010011 ,
b01000 1
1Y
0]
#2
b00000000000000000000010100010011 #
b00000000000000000000000000000100 +
b01010 1
1]
#3
0]
#4
b00000000000000000000010110010011 #
b00000000000000000000000000001000 +
b01011 1
1]
#5
0]
#6
b00000000100000000000001010010011 #
b00000000000000000000000000001100 +
b01000 0
b00101 1
b00000000000000000000000000001000 X
0Y
b00000000000000000000000000001000 [
b00000000000000000000000000001000 \
1]
b00000000000000000000000000001000 a
b00000000000000000000000000001000 b
#7
0]
#8
b00000000010000000000011011101111 #
0&
1*
b00000000000000000000000000010000 +
b1101111 ,
b00100 0
b01101 1
b00000000000000000000000000001000 ;
b00000000000000000000011011101110 X
1Y
b100 Z
b00000000000000000000000000000000 [
b00000000000000000000000000000000 \
1]
b00000000000000000000000000000000 a
b00000000000000000000000000000100 b
#9
0]
#10
b00000000000101010000010100010011 #
1&
0*
b00000000000000000000000000010100 +
b0010011 ,
b01010 /
b00001 0
b01010 1
b00000000000000000000000000000100 C
b00000000000000000000000000000001 X
0Y
b000 Z
b00000000000000000000000000000001 [
b00000000000000000000000000000001 \
1]
b00000000000000000000000000000001 a
b00000000000000000000000000000001 b
#11
0]
#12
b00000000110000000000010111101111 #
0&
1*
b00000000000000000000000000011000 +
b1101111 ,
b00000 /
b01100 0
b01011 1
b00000000000000000000000000000001 @
b00000000000000000000010111101110 X
1Y
b100 Z
b00000000000000000000000000000000 [
b00000000000000000000000000000000 \
1]
b00000000000000000000000000000001 _
b00000000000000000000000000000000 a
b00000000000000000000000000000100 b
#13
0]
#14
b00000000010101010001010001100011 #
0$
0*
b00000000000000000000000000011100 +
b1100011 ,
b0001 -
b01010 /
b00101 0
b01000 1
b00000000000000000000000000000001 4
b00000000000000000000000000001000 5
b00000000000000000000000000000100 A
1W
b00000000000000000000000000001000 X
0Y
b010 Z
b00000000000000000000000000001001 [
b00000000000000000000000000001000 \
1]
b00000000000000000000000000001001 a
b00000000000000000000000000001001 b
#15
0]
#16
b00000000000101000001010000010011 #
1$
b110 %
1&
b00000000000000000000000000100100 +
b0010011 ,
b01000 /
b00001 0
b00000000000000000000000000000000 4
b00000000000000000000000000000000 5
0W
b00000000000000000000000000000001 X
b000 Z
b00000000000000000000000000000000 [
b00000000000000000000000000000001 \
1]
b00000000000000000000000000000000 a
b00000000000000000000000000000000 b
#17
0]
#18
b00000000000101000000010000010011 #
b000 %
b00000000000000000000000000101000 +
b0000 -
b00000000000000000000000000000001 [
1]
b00000000000000000000000000000001 a
b00000000000000000000000000000001 b
#19
0]
#20
b00000000000000000001010001100011 #
0$
0&
b00000000000000000000000000101100 +
b1100011 ,
b0001 -
b00000 /
b00000 0
b00000000000000000000000000000001 >
b00000000000000000000000000000000 X
1Y
b00000000000000000000000000000000 [
b00000000000000000000000000000000 \
1]
b00000000000000000000000000000000 a
b00000000000000000000000000000000 b
#21
0]
#22
b11111101000111111111000000000000 #
b00000000000000000000000000110000 +
b0000000 ,
b0111 -
1.
b11111 /
b10001 0
b00000 1
b11111111111111111111111111010001 X
1]
#23
0]
#24
b00000000000000000000000000000000 #
b00000000000000000000000000110100 +
b0000 -
0.
b00000 /
b00000 0
b00000000000000000000000000000000 X
1]
#25
0]
#26
b00000000000000000000000000111000 +
1]
#27
0]
#28
b00000000000000000000000000111100 +
1]
#29
0]
#30
b00000000000000000000010000010011 #
1$
1&
b00000000000000000000000001000000 +
b0010011 ,
b01000 1
1]
#31
0]
#32
b00000000000000000000010100010011 #
b00000000000000000000000001000100 +
b01010 1
b00000000000000000000000000000000 >
1]
#33
0]
#34
b00000000000000000000010110010011 #
b00000000000000000000000001001000 +
b01011 1
b00000000000000000000000000000000 @
1]
b00000000000000000000000000000000 _
#35
0]
#36
b00000000100000000000001010010011 #
b00000000000000000000000001001100 +
b01000 0
b00101 1
b00000000000000000000000000000000 A
b00000000000000000000000000001000 X
0Y
b00000000000000000000000000001000 [
b00000000000000000000000000001000 \
1]
b00000000000000000000000000001000 a
b00000000000000000000000000001000 b
#37
0]
#38
b00000000010000000000011011101111 #
0&
1*
b00000000000000000000000001010000 +
b1101111 ,
b00100 0
b01101 1
b00000000000000000000011011101110 X
1Y
b100 Z
b00000000000000000000000000000000 [
b00000000000000000000000000000000 \
1]
b00000000000000000000000000000000 a
b00000000000000000000000000000100 b
#39
0]
#40
b00000000000101010000010100010011 #
1&
0*
b00000000000000000000000001010100 +
b0010011 ,
b01010 /
b00001 0
b01010 1
b00000000000000000000000000000001 X
0Y
b000 Z
b00000000000000000000000000000001 [
b00000000000000000000000000000001 \
1]
b00000000000000000000000000000001 a
b00000000000000000000000000000001 b
#41
0]
#42
b00000000110000000000010111101111 #
0&
1*
b00000000000000000000000001011000 +
b1101111 ,
b00000 /
b01100 0
b01011 1
b00000000000000000000000000000001 @
b00000000000000000000010111101110 X
1Y
b100 Z
b00000000000000000000000000000000 [
b00000000000000000000000000000000 \
1]
1^
b00000000000000000000000000000001 _
b00000000000000000000000000000000 a
b00000000000000000000000000000100 b
#43
0]
#44
b00000000000000000000010000010011 #
1&
0*
b00000000000000000000000000000000 +
b0010011 ,
b00000 0
b01000 1
b00000000000000000000000000000100 A
b00000000000000000000000000000000 X
b000 Z
1]
0^
b00000000000000000000000000000000 b
#45
0]
#46
b00000000000000000000010100010011 #
b00000000000000000000000000000100 +
b01010 1
1]
#47
0]
#48
b00000000000000000000010110010011 #
b00000000000000000000000000001000 +
b01011 1
b00000000000000000000000000000000 @
1]
b00000000000000000000000000000000 _
#49
0]
#50
b00000000100000000000001010010011 #
b00000000000000000000000000001100 +
b01000 0
b00101 1
b00000000000000000000000000000000 A
b00000000000000000000000000001000 X
0Y
b00000000000000000000000000001000 [
b00000000000000000000000000001000 \
1]
b00000000000000000000000000001000 a
b00000000000000000000000000001000 b
#51
0]
#52
b00000000010000000000011011101111 #
0&
1*
b00000000000000000000000000010000 +
b1101111 ,
b00100 0
b01101 1
b00000000000000000000011011101110 X
1Y
b100 Z
b00000000000000000000000000000000 [
b00000000000000000000000000000000 \
1]
b00000000000000000000000000000000 a
b00000000000000000000000000000100 b
#53
0]
#54
b00000000000101010000010100010011 #
1&
0*
b00000000000000000000000000010100 +
b0010011 ,
b01010 /
b00001 0
b01010 1
b00000000000000000000000000000001 X
0Y
b000 Z
b00000000000000000000000000000001 [
b00000000000000000000000000000001 \
1]
b00000000000000000000000000000001 a
b00000000000000000000000000000001 b
#55
0]
#56
b00000000110000000000010111101111 #
0&
1*
b00000000000000000000000000011000 +
b1101111 ,
b00000 /
b01100 0
b01011 1
b00000000000000000000000000000001 @
b00000000000000000000010111101110 X
1Y
b100 Z
b00000000000000000000000000000000 [
b00000000000000000000000000000000 \
1]
b00000000000000000000000000000001 _
b00000000000000000000000000000000 a
b00000000000000000000000000000100 b
#57
0]
#58
b00000000010101010001010001100011 #
0$
0*
b00000000000000000000000000011100 +
b1100011 ,
b0001 -
b01010 /
b00101 0
b01000 1
b00000000000000000000000000000001 4
b00000000000000000000000000001000 5
b00000000000000000000000000000100 A
1W
b00000000000000000000000000001000 X
0Y
b010 Z
b00000000000000000000000000001001 [
b00000000000000000000000000001000 \
1]
b00000000000000000000000000001001 a
b00000000000000000000000000001001 b
#59
0]
#60
b00000000000101000001010000010011 #
1$
b110 %
1&
b00000000000000000000000000100100 +
b0010011 ,
b01000 /
b00001 0
b00000000000000000000000000000000 4
b00000000000000000000000000000000 5
0W
b00000000000000000000000000000001 X
b000 Z
b00000000000000000000000000000000 [
b00000000000000000000000000000001 \
1]
b00000000000000000000000000000000 a
b00000000000000000000000000000000 b
#61
0]
#62
b00000000000101000000010000010011 #
b000 %
b00000000000000000000000000101000 +
b0000 -
b00000000000000000000000000000001 [
1]
b00000000000000000000000000000001 a
b00000000000000000000000000000001 b
#63
0]
