fullcpu/mux.sv
module mux #(
    parameter DATA_WIDTH = 32
)(
    // interface signals
    input logic   [DATA_WIDTH-1:0]        d0,     // regOp2
    input logic   [DATA_WIDTH-1:0]        d1,     // ImmOp
    input logic                           s,      // ALUsrc
    output logic  [DATA_WIDTH-1:0]        out    // ALUop2
);

    // output logic
    assign out = s ? d1 : d0;

endmodule

fullcpu/datamem.sv
module datamem#(
    parameter   ADDRESS_WIDTH = 32,
                DATA_WIDTH = 32
)(
    input logic clk,
    input logic wr_en,
    input logic [ADDRESS_WIDTH-1:0] addr,
    input logic [DATA_WIDTH-1:0] wd,
    output logic [DATA_WIDTH-1:0] rd 
);

logic [DATA_WIDTH-1:0] ram_array [255:0];

assign ram_array[255] = 32'h12345; // a0 should be 12345 after FE

always_ff @(posedge clk) begin 
    if(wr_en == 1'b1)
        ram_array[addr] <= wd;
end
assign rd = ram_array [addr];
endmodule

fullcpu/alu.sv
module alu #(
    parameter DATA_WIDTH = 32
)(
    // interface signals
    input logic        [DATA_WIDTH-1:0]         ALUop1,       // rd1
    input logic        [DATA_WIDTH-1:0]         ALUop2,       
    input logic        [2:0]                    ALUCtrl,      
    output logic                                eq,
    output logic       [DATA_WIDTH-1:0]         out           // ALUout
);

    always_comb begin
        // SUM
        if(ALUCtrl == 3'b000)
            out = ALUop1 + ALUop2;
        
        // EQ
        if(ALUop1 == ALUop2)
            eq = 1;
        else 
            eq = 0;
        
    end

endmodule

fullcpu/regfile.sv
module regfile #(
    parameter ADDRESS_WIDTH = 5,
    parameter DATA_WIDTH = 32
)(
    // interface signals
    input logic                           clk,
    input logic   [ADDRESS_WIDTH-1:0]     addr1,     // rs1
    input logic   [ADDRESS_WIDTH-1:0]     addr2,     // rs2
    input logic   [ADDRESS_WIDTH-1:0]     addr3,     // rd
    input logic                           we3,       // RegWrite
    input logic   [DATA_WIDTH-1:0]        wd3,       // ALUout
    output logic  [DATA_WIDTH-1:0]        rd1,
    output logic  [DATA_WIDTH-1:0]        rd2,
    output logic  [DATA_WIDTH-1:0]        a0
);

    // state registers
    logic [DATA_WIDTH-1:0] ram_array [2**ADDRESS_WIDTH-1:0];

    always_ff @(posedge clk) begin
        if (we3) ram_array[addr3] <= wd3; 
    end

    always_comb begin
        rd1 = (addr1 == 0) ? 0 : ram_array[addr1];
        rd2 = (addr2 == 0) ? 0 : ram_array[addr2];
        a0 = ram_array[10];
    end

endmodule

fullcpu/topregalu.sv
module topregalu #(
    parameter   DATA_WIDTH = 32,
                ADDRESS_WIDTH = 5
)(
    // interface signals
    input logic                                      clk,
    input logic        [ADDRESS_WIDTH-1:0]           rs1,           
    input logic        [ADDRESS_WIDTH-1:0]           rs2,      
    input logic        [ADDRESS_WIDTH-1:0]           rd,
    input logic                                      RegWrite,
    input logic                                      ALUsrc,
    input logic                                      ResultSrc,
    input logic                                      MemWrite,   
    input logic        [2:0]                         ALUCtrl,
    input logic        [DATA_WIDTH-1:0]              ImmOp,
    output logic                                     eq,
    output logic       [DATA_WIDTH-1:0]              a0
);

logic [DATA_WIDTH-1:0] ALUout;
logic [DATA_WIDTH-1:0] ALUop1;
logic [DATA_WIDTH-1:0] ALUop2;
logic [DATA_WIDTH-1:0] regOp2;
logic [DATA_WIDTH-1:0] ReadData;
logic [DATA_WIDTH-1:0] Results; // output from the result mux

regfile RegFile (
    .clk(clk),
    .addr1(rs1),
    .addr2(rs2),
    .addr3(rd),
    .we3(RegWrite),
    .wd3(Results),
    .rd1(ALUop1),
    .rd2(regOp2),
    .a0(a0)
);

alu ALU(
    .ALUop1(ALUop1),
    .ALUop2(ALUop2),
    .ALUCtrl(ALUCtrl),
    .eq(eq),
    .out(ALUout)
);

mux MUX(
    .d0(regOp2),
    .d1(ImmOp),
    .s(ALUsrc),
    .out(ALUop2)
);

datamem datamemory(
    .clk(clk),
    .wr_en(MemWrite),
    .addr(ALUout),
    .wd(regOp2),
    .rd(ReadData)
);

mux ResultMux(
    .d0(ALUout),
    .d1(ReadData),
    .s(ResultSrc),
    .out(Results)
);

endmodule

fullcpu/sign_extend.sv
module sign_extend #(
    parameter address_width = 32
)(
    input logic     [address_width-1:0]        instr,  //output from Instr Mem
    input logic     [2:0]                      ImmSrc,
    output logic    [address_width-1:0]        ImmOp   //input to PC and ALUsrc mux
);

always_comb begin
    if (ImmSrc == 3'b000)
        begin
        ImmOp[31:12] = {20{instr[address_width-1]}};
        ImmOp[11:0] = instr[address_width-1:20];
        end
    else if (ImmSrc == 3'b010)
        begin
        ImmOp[31:13] = {19{instr[address_width-1]}};
        ImmOp[12:0] = {instr[address_width-1], instr[7], instr[30:25], instr[11:8],1'b0};
        end    
end

endmodule

fullcpu/control_unit.sv
module control_unit #(
    parameter address_width = 7
)(
    input logic      [address_width-1:0]   instr,  //output from Instr Mem
    input logic         EQ,
    output logic        RegWrite,
    output logic       [2:0] ALUctrl,
    output logic        ALUsrc,
    output logic       [2:0] ImmSrc,
    output logic        PCsrc,
    output logic        MemWrite,
    output logic        ResultSrc
);

always_comb begin
    RegWrite = 1'b0;
    ImmSrc = 3'b000;
    ALUctrl = 3'b000;
    ALUsrc = 1'b0;
    PCsrc = 1'b0; 
    MemWrite = 1'b0;
    ResultSrc = 1'b0;
    if(instr[6:0] == 7'b0010011) // addi
        begin 
        RegWrite = 1'b1;
        ImmSrc = 3'b000;
        ALUctrl = 3'b000;
        ALUsrc = 1'b1;
        end
    if(instr[6:0] == 7'b1100011) // bne
        if(EQ == 1'b0)
        begin
            ImmSrc = 3'b010;
            PCsrc = 1'b1;
        end
    if(instr[6:0] == 7'b0100011) // sw 
        MemWrite = 1'b1;
    if(instr[6:0] == 7'b0000011) // lw 
        ResultSrc = 1'b1;
        RegWrite = 1'b1;
end 

endmodule

fullcpu/instr_mem.sv
module instr_mem #(
    parameter   ADDRESS_WIDTH = 32, //testing
                DATAOUT_WIDTH = 32,
                DATA_WIDTH = 8
)(
    input logic [ADDRESS_WIDTH-1:0] A,
    output logic [DATAOUT_WIDTH-1:0] RD
);

logic [DATA_WIDTH-1:0] rom_array [27:0];

initial begin
        
        $display("Loading rom.");
        $readmemh("test1.mem", rom_array);
        //rom_array[28:2**32-1] <= '{default:'1};
end;

assign RD = {rom_array [A],rom_array [A+1],rom_array [A+2],rom_array [A+3]};

endmodule

fullcpu/blue_part.sv
module blue_part #(
    parameter address_width = 32
)(
    input logic                            PCsrc, // output from control unit
    input logic                            clk,
    input logic                            rst,
    input logic [address_width-1:0]        ImmOp, // output from "sign extend" block
    output logic [address_width-1:0]       PC
);

//logic       next_pc;

always_ff@(posedge clk) begin
    if (rst)        PC <= {address_width{1'b0}};
    else if (PCsrc)      PC <= PC + ImmOp;
    else            PC <= PC + 4;
end

endmodule

fullcpu/top.sv
module top#(
    parameter ADDRESS_WIDTH = 32,
    DATAOUT_WIDTH = 32
)(
    input logic                            PCsrc, // output from control unit
    input logic                            clk,
    input logic                            rst,
    input logic [DATAOUT_WIDTH-1:0]        ImmOp, // output from "sign extend" block
  //  output logic [ADDRESS_WIDTH-1:0]       PC,
  //  input logic [ADDRESS_WIDTH-1:0]        A,
    output logic [DATAOUT_WIDTH-1:0]       RD
);

logic [ADDRESS_WIDTH-1:0]        A;

blue_part pc(
    .PCsrc(PCsrc),
    .clk(clk),
    .rst(rst),
    .ImmOp(ImmOp),
    .PC(A)
);

instr_mem mem(
    .A(A),
    .RD(RD)
);

endmodule

fullcpu/fullcpu.sv
module fullcpu#(
    parameter  DATA_WIDTH = 32
) (
    input logic clk,
    input logic rst,
    output [DATA_WIDTH-1:0] a0
);

logic PCsrc;
logic [DATA_WIDTH-1:0] ImmOp;
logic [DATA_WIDTH-1:0] Instr;
logic EQ;
logic RegWrite;
logic [2:0] ALUctrl;
logic ALUsrc;
logic [2:0] ImmSrc;
logic MemWrite;
logic ResultSrc;

top blue(
    .PCsrc(PCsrc),
    .clk(clk),
    .rst(rst),
    .ImmOp(ImmOp),
    .RD(Instr)
);

control_unit controlunit(
    .instr(Instr[6:0]),
    .EQ(EQ),
    .RegWrite(RegWrite),
    .ALUctrl(ALUctrl),
    .ALUsrc(ALUsrc),
    .ImmSrc(ImmSrc),
    .PCsrc(PCsrc),
    .MemWrite(MemWrite),
    .ResultSrc(ResultSrc)
);

sign_extend signextend (
    .instr(Instr),
    .ImmSrc(ImmSrc),
    .ImmOp(ImmOp)
);

topregalu topregalu (
    .clk(clk),
    .rs1(Instr[19:15]),
    .rs2(Instr[24:20]),
    .rd(Instr[11:7]),
    .RegWrite(RegWrite),
    .ALUsrc(ALUsrc),
    .ResultSrc(ResultSrc),
    .MemWrite(MemWrite),
    .ALUCtrl(ALUctrl),
    .ImmOp(ImmOp),
    .eq(EQ),
    .a0(a0)
);

endmodule

fullcpu/fullcpu.vcd
$version Generated by VerilatedVcd $end
$date Thu Nov 24 19:11:00 2022 $end
$timescale 1ps $end

 $scope module TOP $end
  $var wire 32 t a0 [31:0] $end
  $var wire  1 r clk $end
  $var wire  1 s rst $end
  $scope module fullcpu $end
   $var wire  3 A ALUctrl [2:0] $end
   $var wire  1 B ALUsrc $end
   $var wire 32 w DATA_WIDTH [31:0] $end
   $var wire  1 n EQ $end
   $var wire 32 m ImmOp [31:0] $end
   $var wire  3 o ImmSrc [2:0] $end
   $var wire 32 ? Instr [31:0] $end
   $var wire  1 C MemWrite $end
   $var wire  1 l PCsrc $end
   $var wire  1 @ RegWrite $end
   $var wire  1 D ResultSrc $end
   $var wire 32 t a0 [31:0] $end
   $var wire  1 r clk $end
   $var wire  1 s rst $end
   $scope module blue $end
    $var wire 32 E A [31:0] $end
    $var wire 32 w ADDRESS_WIDTH [31:0] $end
    $var wire 32 w DATAOUT_WIDTH [31:0] $end
    $var wire 32 m ImmOp [31:0] $end
    $var wire  1 l PCsrc $end
    $var wire 32 ? RD [31:0] $end
    $var wire  1 r clk $end
    $var wire  1 s rst $end
    $scope module mem $end
     $var wire 32 E A [31:0] $end
     $var wire 32 w ADDRESS_WIDTH [31:0] $end
     $var wire 32 w DATAOUT_WIDTH [31:0] $end
     $var wire 32 x DATA_WIDTH [31:0] $end
     $var wire 32 ? RD [31:0] $end
     $var wire  8 # rom_array[0] [7:0] $end
     $var wire  8 - rom_array[10] [7:0] $end
     $var wire  8 . rom_array[11] [7:0] $end
     $var wire  8 / rom_array[12] [7:0] $end
     $var wire  8 0 rom_array[13] [7:0] $end
     $var wire  8 1 rom_array[14] [7:0] $end
     $var wire  8 2 rom_array[15] [7:0] $end
     $var wire  8 3 rom_array[16] [7:0] $end
     $var wire  8 4 rom_array[17] [7:0] $end
     $var wire  8 5 rom_array[18] [7:0] $end
     $var wire  8 6 rom_array[19] [7:0] $end
     $var wire  8 $ rom_array[1] [7:0] $end
     $var wire  8 7 rom_array[20] [7:0] $end
     $var wire  8 8 rom_array[21] [7:0] $end
     $var wire  8 9 rom_array[22] [7:0] $end
     $var wire  8 : rom_array[23] [7:0] $end
     $var wire  8 ; rom_array[24] [7:0] $end
     $var wire  8 < rom_array[25] [7:0] $end
     $var wire  8 = rom_array[26] [7:0] $end
     $var wire  8 > rom_array[27] [7:0] $end
     $var wire  8 % rom_array[2] [7:0] $end
     $var wire  8 & rom_array[3] [7:0] $end
     $var wire  8 ' rom_array[4] [7:0] $end
     $var wire  8 ( rom_array[5] [7:0] $end
     $var wire  8 ) rom_array[6] [7:0] $end
     $var wire  8 * rom_array[7] [7:0] $end
     $var wire  8 + rom_array[8] [7:0] $end
     $var wire  8 , rom_array[9] [7:0] $end
    $upscope $end
    $scope module pc $end
     $var wire 32 m ImmOp [31:0] $end
     $var wire 32 E PC [31:0] $end
     $var wire  1 l PCsrc $end
     $var wire 32 w address_width [31:0] $end
     $var wire  1 r clk $end
     $var wire  1 s rst $end
    $upscope $end
   $upscope $end
   $scope module controlunit $end
    $var wire  3 A ALUctrl [2:0] $end
    $var wire  1 B ALUsrc $end
    $var wire  1 n EQ $end
    $var wire  3 o ImmSrc [2:0] $end
    $var wire  1 C MemWrite $end
    $var wire  1 l PCsrc $end
    $var wire  1 @ RegWrite $end
    $var wire  1 D ResultSrc $end
    $var wire 32 y address_width [31:0] $end
    $var wire  7 F instr [6:0] $end
   $upscope $end
   $scope module signextend $end
    $var wire 32 m ImmOp [31:0] $end
    $var wire  3 o ImmSrc [2:0] $end
    $var wire 32 w address_width [31:0] $end
    $var wire 32 ? instr [31:0] $end
   $upscope $end
   $scope module topregalu $end
    $var wire 32 z ADDRESS_WIDTH [31:0] $end
    $var wire  3 A ALUCtrl [2:0] $end
    $var wire 32 J ALUop1 [31:0] $end
    $var wire 32 q ALUop2 [31:0] $end
    $var wire 32 p ALUout [31:0] $end
    $var wire  1 B ALUsrc $end
    $var wire 32 w DATA_WIDTH [31:0] $end
    $var wire 32 m ImmOp [31:0] $end
    $var wire  1 C MemWrite $end
    $var wire 32 u ReadData [31:0] $end
    $var wire  1 @ RegWrite $end
    $var wire  1 D ResultSrc $end
    $var wire 32 v Results [31:0] $end
    $var wire 32 t a0 [31:0] $end
    $var wire  1 r clk $end
    $var wire  1 n eq $end
    $var wire  5 I rd [4:0] $end
    $var wire 32 K regOp2 [31:0] $end
    $var wire  5 G rs1 [4:0] $end
    $var wire  5 H rs2 [4:0] $end
    $scope module ALU $end
     $var wire  3 A ALUCtrl [2:0] $end
     $var wire 32 J ALUop1 [31:0] $end
     $var wire 32 q ALUop2 [31:0] $end
     $var wire 32 w DATA_WIDTH [31:0] $end
     $var wire  1 n eq $end
     $var wire 32 p out [31:0] $end
    $upscope $end
    $scope module MUX $end
     $var wire 32 w DATA_WIDTH [31:0] $end
     $var wire 32 K d0 [31:0] $end
     $var wire 32 m d1 [31:0] $end
     $var wire 32 q out [31:0] $end
     $var wire  1 B s $end
    $upscope $end
    $scope module RegFile $end
     $var wire 32 z ADDRESS_WIDTH [31:0] $end
     $var wire 32 w DATA_WIDTH [31:0] $end
     $var wire 32 t a0 [31:0] $end
     $var wire  5 G addr1 [4:0] $end
     $var wire  5 H addr2 [4:0] $end
     $var wire  5 I addr3 [4:0] $end
     $var wire  1 r clk $end
     $var wire 32 L ram_array[0] [31:0] $end
     $var wire 32 V ram_array[10] [31:0] $end
     $var wire 32 W ram_array[11] [31:0] $end
     $var wire 32 X ram_array[12] [31:0] $end
     $var wire 32 Y ram_array[13] [31:0] $end
     $var wire 32 Z ram_array[14] [31:0] $end
     $var wire 32 [ ram_array[15] [31:0] $end
     $var wire 32 \ ram_array[16] [31:0] $end
     $var wire 32 ] ram_array[17] [31:0] $end
     $var wire 32 ^ ram_array[18] [31:0] $end
     $var wire 32 _ ram_array[19] [31:0] $end
     $var wire 32 M ram_array[1] [31:0] $end
     $var wire 32 ` ram_array[20] [31:0] $end
     $var wire 32 a ram_array[21] [31:0] $end
     $var wire 32 b ram_array[22] [31:0] $end
     $var wire 32 c ram_array[23] [31:0] $end
     $var wire 32 d ram_array[24] [31:0] $end
     $var wire 32 e ram_array[25] [31:0] $end
     $var wire 32 f ram_array[26] [31:0] $end
     $var wire 32 g ram_array[27] [31:0] $end
     $var wire 32 h ram_array[28] [31:0] $end
     $var wire 32 i ram_array[29] [31:0] $end
     $var wire 32 N ram_array[2] [31:0] $end
     $var wire 32 j ram_array[30] [31:0] $end
     $var wire 32 k ram_array[31] [31:0] $end
     $var wire 32 O ram_array[3] [31:0] $end
     $var wire 32 P ram_array[4] [31:0] $end
     $var wire 32 Q ram_array[5] [31:0] $end
     $var wire 32 R ram_array[6] [31:0] $end
     $var wire 32 S ram_array[7] [31:0] $end
     $var wire 32 T ram_array[8] [31:0] $end
     $var wire 32 U ram_array[9] [31:0] $end
     $var wire 32 J rd1 [31:0] $end
     $var wire 32 K rd2 [31:0] $end
     $var wire 32 v wd3 [31:0] $end
     $var wire  1 @ we3 $end
    $upscope $end
    $scope module ResultMux $end
     $var wire 32 w DATA_WIDTH [31:0] $end
     $var wire 32 p d0 [31:0] $end
     $var wire 32 u d1 [31:0] $end
     $var wire 32 v out [31:0] $end
     $var wire  1 D s $end
    $upscope $end
    $scope module datamemory $end
     $var wire 32 w ADDRESS_WIDTH [31:0] $end
     $var wire 32 w DATA_WIDTH [31:0] $end
     $var wire 32 p addr [31:0] $end
     $var wire  1 r clk $end
     $var wire 32 u rd [31:0] $end
     $var wire 32 K wd [31:0] $end
     $var wire  1 C wr_en $end
    $upscope $end
   $upscope $end
  $upscope $end
 $upscope $end
$enddefinitions $end


#0
b00000000 #
b00000000 $
b00000000 %
b00000000 &
b00000000 '
b00000000 (
b00000000 )
b00000000 *
b00000000 +
b00000000 ,
b00000000 -
b00000000 .
b00000000 /
b00000000 0
b00000000 1
b00000000 2
b00000000 3
b00000000 4
b00000000 5
b00000000 6
b00000000 7
b00000000 8
b00000000 9
b00000000 :
b00000000 ;
b00000000 <
b00000000 =
b00000000 >
b00000000000000000000000000000000 ?
0@
b000 A
0B
0C
0D
b00000000000000000000000000000000 E
b0000000 F
b00000 G
b00000 H
b00000 I
b00000000000000000000000000000000 J
b00000000000000000000000000000000 K
b00000000000000000000000000000000 L
b00000000000000000000000000000000 M
b00000000000000000000000000000000 N
b00000000000000000000000000000000 O
b00000000000000000000000000000000 P
b00000000000000000000000000000000 Q
b00000000000000000000000000000000 R
b00000000000000000000000000000000 S
b00000000000000000000000000000000 T
b00000000000000000000000000000000 U
b00000000000000000000000000000000 V
b00000000000000000000000000000000 W
b00000000000000000000000000000000 X
b00000000000000000000000000000000 Y
b00000000000000000000000000000000 Z
b00000000000000000000000000000000 [
b00000000000000000000000000000000 \
b00000000000000000000000000000000 ]
b00000000000000000000000000000000 ^
b00000000000000000000000000000000 _
b00000000000000000000000000000000 `
b00000000000000000000000000000000 a
b00000000000000000000000000000000 b
b00000000000000000000000000000000 c
b00000000000000000000000000000000 d
b00000000000000000000000000000000 e
b00000000000000000000000000000000 f
b00000000000000000000000000000000 g
b00000000000000000000000000000000 h
b00000000000000000000000000000000 i
b00000000000000000000000000000000 j
b00000000000000000000000000000000 k
0l
b00000000000000000000000000000000 m
0n
b000 o
b00000000000000000000000000000000 p
b00000000000000000000000000000000 q
1r
0s
b00000000000000000000000000000000 t
b00000000000000000000000000000000 u
b00000000000000000000000000000000 v
b00000000000000000000000000100000 w
b00000000000000000000000000001000 x
b00000000000000000000000000000111 y
b00000000000000000000000000000101 z
#1
b00001111 #
b11110000 $
b00000011 %
b00010011 &
b00000101 )
b00010011 *
b00000101 -
b10010011 .
b00000101 0
b10000101 1
b00010011 2
b00010101 4
b10000101 5
b10010011 6
b11111110 7
b01100101 8
b10011100 9
b11100011 :
b00000101 <
b10100101 =
b00000011 >
b00001111111100000000001100010011 ?
1@
1B
b0010011 F
b11111 H
b00110 I
b00000000000000000000000011111111 m
b00000000000000000000000011111111 p
b00000000000000000000000011111111 q
0r
b00000000000000010010001101000101 u
b00000000000000000000000011111111 v
#2
b00000000000000000000010100010011 ?
b00000000000000000000000000000100 E
b00000 H
b01010 I
b00000000000000000000000011111111 R
b00000000000000000000000000000000 m
1n
b00000000000000000000000000000000 p
b00000000000000000000000000000000 q
1r
b00000000000000000000000000000000 u
b00000000000000000000000000000000 v
#3
0r
#4
b00000000000000000000010110010011 ?
b00000000000000000000000000001000 E
b01011 I
1r
#5
0r
#6
b00000000000001011000010100010011 ?
b00000000000000000000000000001100 E
b01011 G
b01010 I
1r
#7
0r
#8
b00000000000101011000010110010011 ?
b00000000000000000000000000010000 E
b00001 H
b01011 I
b00000000000000000000000000000001 m
0n
b00000000000000000000000000000001 p
b00000000000000000000000000000001 q
1r
b00000000000000000000000000000001 v
#9
0r
#10
b11111110011001011001110011100011 ?
0B
b00000000000000000000000000010100 E
b1100011 F
b00110 H
b11001 I
b00000000000000000000000000000001 J
b00000000000000000000000011111111 K
b00000000000000000000000000000001 W
1l
b11111111111111111111111111111000 m
b010 o
b00000000000000000000000100000000 p
b00000000000000000000000011111111 q
1r
b00000000000000000000000100000000 v
#11
0r
#12
b00000000000001011000010100010011 ?
1B
b00000000000000000000000000001100 E
b0010011 F
b00000 H
b01010 I
b00000000000000000000000000000000 K
b00000000000000000000000100000000 e
0l
b00000000000000000000000000000000 m
b000 o
b00000000000000000000000000000001 p
b00000000000000000000000000000000 q
1r
b00000000000000000000000000000001 v
#13
0r
#14
b00000000000101011000010110010011 ?
b00000000000000000000000000010000 E
b00001 H
b01011 I
b00000000000000000000000000000001 V
b00000000000000000000000000000001 m
1n
b00000000000000000000000000000010 p
b00000000000000000000000000000001 q
1r
b00000000000000000000000000000001 t
b00000000000000000000000000000010 v
#15
0r
#16
b11111110011001011001110011100011 ?
0B
b00000000000000000000000000010100 E
b1100011 F
b00110 H
b11001 I
b00000000000000000000000000000010 J
b00000000000000000000000011111111 K
b00000000000000000000000000000010 W
1l
b11111111111111111111111111111000 m
0n
b010 o
b00000000000000000000000100000001 p
b00000000000000000000000011111111 q
1r
b00000000000000000000000100000001 v
#17
0r
#18
b00000000000001011000010100010011 ?
1B
b00000000000000000000000000001100 E
b0010011 F
b00000 H
b01010 I
b00000000000000000000000000000000 K
b00000000000000000000000100000001 e
0l
b00000000000000000000000000000000 m
b000 o
b00000000000000000000000000000010 p
b00000000000000000000000000000000 q
1r
b00000000000000000000000000000010 v
#19
0r
#20
b00000000000101011000010110010011 ?
b00000000000000000000000000010000 E
b00001 H
b01011 I
b00000000000000000000000000000010 V
b00000000000000000000000000000001 m
b00000000000000000000000000000011 p
b00000000000000000000000000000001 q
1r
b00000000000000000000000000000010 t
b00000000000000000000000000000011 v
#21
0r
#22
b11111110011001011001110011100011 ?
0B
b00000000000000000000000000010100 E
b1100011 F
b00110 H
b11001 I
b00000000000000000000000000000011 J
b00000000000000000000000011111111 K
b00000000000000000000000000000011 W
1l
b11111111111111111111111111111000 m
b010 o
b00000000000000000000000100000010 p
b00000000000000000000000011111111 q
1r
b00000000000000000000000100000010 v
#23
0r
#24
b00000000000001011000010100010011 ?
1B
b00000000000000000000000000001100 E
b0010011 F
b00000 H
b01010 I
b00000000000000000000000000000000 K
b00000000000000000000000100000010 e
0l
b00000000000000000000000000000000 m
b000 o
b00000000000000000000000000000011 p
b00000000000000000000000000000000 q
1r
b00000000000000000000000000000011 v
#25
0r
#26
b00000000000101011000010110010011 ?
b00000000000000000000000000010000 E
b00001 H
b01011 I
b00000000000000000000000000000011 V
b00000000000000000000000000000001 m
b00000000000000000000000000000100 p
b00000000000000000000000000000001 q
1r
b00000000000000000000000000000011 t
b00000000000000000000000000000100 v
#27
0r
#28
b11111110011001011001110011100011 ?
0B
b00000000000000000000000000010100 E
b1100011 F
b00110 H
b11001 I
b00000000000000000000000000000100 J
b00000000000000000000000011111111 K
b00000000000000000000000000000100 W
1l
b11111111111111111111111111111000 m
b010 o
b00000000000000000000000100000011 p
b00000000000000000000000011111111 q
1r
b00000000000000000000000100000011 v
#29
0r
#30
b00000000000001011000010100010011 ?
1B
b00000000000000000000000000001100 E
b0010011 F
b00000 H
b01010 I
b00000000000000000000000000000000 K
b00000000000000000000000100000011 e
0l
b00000000000000000000000000000000 m
b000 o
b00000000000000000000000000000100 p
b00000000000000000000000000000000 q
1r
b00000000000000000000000000000100 v
#31
0r
#32
b00000000000101011000010110010011 ?
b00000000000000000000000000010000 E
b00001 H
b01011 I
b00000000000000000000000000000100 V
b00000000000000000000000000000001 m
b00000000000000000000000000000101 p
b00000000000000000000000000000001 q
1r
b00000000000000000000000000000100 t
b00000000000000000000000000000101 v
#33
0r
#34
b11111110011001011001110011100011 ?
0B
b00000000000000000000000000010100 E
b1100011 F
b00110 H
b11001 I
b00000000000000000000000000000101 J
b00000000000000000000000011111111 K
b00000000000000000000000000000101 W
1l
b11111111111111111111111111111000 m
b010 o
b00000000000000000000000100000100 p
b00000000000000000000000011111111 q
1r
b00000000000000000000000100000100 v
#35
0r
#36
b00000000000001011000010100010011 ?
1B
b00000000000000000000000000001100 E
b0010011 F
b00000 H
b01010 I
b00000000000000000000000000000000 K
b00000000000000000000000100000100 e
0l
b00000000000000000000000000000000 m
b000 o
b00000000000000000000000000000101 p
b00000000000000000000000000000000 q
1r
b00000000000000000000000000000101 v
#37
0r
#38
b00000000000101011000010110010011 ?
b00000000000000000000000000010000 E
b00001 H
b01011 I
b00000000000000000000000000000101 V
b00000000000000000000000000000001 m
b00000000000000000000000000000110 p
b00000000000000000000000000000001 q
1r
b00000000000000000000000000000101 t
b00000000000000000000000000000110 v
#39
0r
#40
b11111110011001011001110011100011 ?
0B
b00000000000000000000000000010100 E
b1100011 F
b00110 H
b11001 I
b00000000000000000000000000000110 J
b00000000000000000000000011111111 K
b00000000000000000000000000000110 W
1l
b11111111111111111111111111111000 m
b010 o
b00000000000000000000000100000101 p
b00000000000000000000000011111111 q
1r
b00000000000000000000000100000101 v
#41
0r
#42
b00000000000001011000010100010011 ?
1B
b00000000000000000000000000001100 E
b0010011 F
b00000 H
b01010 I
b00000000000000000000000000000000 K
b00000000000000000000000100000101 e
0l
b00000000000000000000000000000000 m
b000 o
b00000000000000000000000000000110 p
b00000000000000000000000000000000 q
1r
1s
b00000000000000000000000000000110 v
#43
0r
#44
b00001111111100000000001100010011 ?
b00000000000000000000000000000000 E
b00000 G
b11111 H
b00110 I
b00000000000000000000000000000000 J
b00000000000000000000000000000110 V
b00000000000000000000000011111111 m
b00000000000000000000000011111111 p
b00000000000000000000000011111111 q
1r
0s
b00000000000000000000000000000110 t
b00000000000000010010001101000101 u
b00000000000000000000000011111111 v
#45
0r
#46
b00000000000000000000010100010011 ?
b00000000000000000000000000000100 E
b00000 H
b01010 I
b00000000000000000000000000000000 m
1n
b00000000000000000000000000000000 p
b00000000000000000000000000000000 q
1r
b00000000000000000000000000000000 u
b00000000000000000000000000000000 v
#47
0r
#48
b00000000000000000000010110010011 ?
b00000000000000000000000000001000 E
b01011 I
b00000000000000000000000000000000 V
1r
b00000000000000000000000000000000 t
#49
0r
#50
b00000000000001011000010100010011 ?
b00000000000000000000000000001100 E
b01011 G
b01010 I
b00000000000000000000000000000000 W
1r
#51
0r
#52
b00000000000101011000010110010011 ?
b00000000000000000000000000010000 E
b00001 H
b01011 I
b00000000000000000000000000000001 m
0n
b00000000000000000000000000000001 p
b00000000000000000000000000000001 q
1r
b00000000000000000000000000000001 v
#53
0r
#54
b11111110011001011001110011100011 ?
0B
b00000000000000000000000000010100 E
b1100011 F
b00110 H
b11001 I
b00000000000000000000000000000001 J
b00000000000000000000000011111111 K
b00000000000000000000000000000001 W
1l
b11111111111111111111111111111000 m
b010 o
b00000000000000000000000100000000 p
b00000000000000000000000011111111 q
1r
b00000000000000000000000100000000 v
#55
0r
#56
b00000000000001011000010100010011 ?
1B
b00000000000000000000000000001100 E
b0010011 F
b00000 H
b01010 I
b00000000000000000000000000000000 K
b00000000000000000000000100000000 e
0l
b00000000000000000000000000000000 m
b000 o
b00000000000000000000000000000001 p
b00000000000000000000000000000000 q
1r
b00000000000000000000000000000001 v
#57
0r
#58
b00000000000101011000010110010011 ?
b00000000000000000000000000010000 E
b00001 H
b01011 I
b00000000000000000000000000000001 V
b00000000000000000000000000000001 m
1n
b00000000000000000000000000000010 p
b00000000000000000000000000000001 q
1r
b00000000000000000000000000000001 t
b00000000000000000000000000000010 v
#59
0r
#60
b11111110011001011001110011100011 ?
0B
b00000000000000000000000000010100 E
b1100011 F
b00110 H
b11001 I
b00000000000000000000000000000010 J
b00000000000000000000000011111111 K
b00000000000000000000000000000010 W
1l
b11111111111111111111111111111000 m
0n
b010 o
b00000000000000000000000100000001 p
b00000000000000000000000011111111 q
1r
b00000000000000000000000100000001 v
#61
0r
#62
b00000000000001011000010100010011 ?
1B
b00000000000000000000000000001100 E
b0010011 F
b00000 H
b01010 I
b00000000000000000000000000000000 K
b00000000000000000000000100000001 e
0l
b00000000000000000000000000000000 m
b000 o
b00000000000000000000000000000010 p
b00000000000000000000000000000000 q
1r
b00000000000000000000000000000010 v
#63
0r
#64
b00000000000101011000010110010011 ?
b00000000000000000000000000010000 E
b00001 H
b01011 I
b00000000000000000000000000000010 V
b00000000000000000000000000000001 m
b00000000000000000000000000000011 p
b00000000000000000000000000000001 q
1r
b00000000000000000000000000000010 t
b00000000000000000000000000000011 v
#65
0r
#66
b11111110011001011001110011100011 ?
0B
b00000000000000000000000000010100 E
b1100011 F
b00110 H
b11001 I
b00000000000000000000000000000011 J
b00000000000000000000000011111111 K
b00000000000000000000000000000011 W
1l
b11111111111111111111111111111000 m
b010 o
b00000000000000000000000100000010 p
b00000000000000000000000011111111 q
1r
b00000000000000000000000100000010 v
#67
0r
#68
b00000000000001011000010100010011 ?
1B
b00000000000000000000000000001100 E
b0010011 F
b00000 H
b01010 I
b00000000000000000000000000000000 K
b00000000000000000000000100000010 e
0l
b00000000000000000000000000000000 m
b000 o
b00000000000000000000000000000011 p
b00000000000000000000000000000000 q
1r
b00000000000000000000000000000011 v
#69
0r
#70
b00000000000101011000010110010011 ?
b00000000000000000000000000010000 E
b00001 H
b01011 I
b00000000000000000000000000000011 V
b00000000000000000000000000000001 m
b00000000000000000000000000000100 p
b00000000000000000000000000000001 q
1r
b00000000000000000000000000000011 t
b00000000000000000000000000000100 v
#71
0r
#72
b11111110011001011001110011100011 ?
0B
b00000000000000000000000000010100 E
b1100011 F
b00110 H
b11001 I
b00000000000000000000000000000100 J
b00000000000000000000000011111111 K
b00000000000000000000000000000100 W
1l
b11111111111111111111111111111000 m
b010 o
b00000000000000000000000100000011 p
b00000000000000000000000011111111 q
1r
b00000000000000000000000100000011 v
#73
0r
